README.rst
setup.cfg
setup.py
doubles/__init__.py
doubles/allowance.py
doubles/call_count_accumulator.py
doubles/class_double.py
doubles/exceptions.py
doubles/expectation.py
doubles/instance_double.py
doubles/lifecycle.py
doubles/method_double.py
doubles/nose.py
doubles/object_double.py
doubles/patch.py
doubles/proxy.py
doubles/proxy_method.py
doubles/proxy_property.py
doubles/pytest_plugin.py
doubles/space.py
doubles/target.py
doubles/testing.py
doubles/unittest.py
doubles/utils.py
doubles/verification.py
doubles.egg-info/PKG-INFO
doubles.egg-info/SOURCES.txt
doubles.egg-info/dependency_links.txt
doubles.egg-info/entry_points.txt
doubles.egg-info/top_level.txt
doubles.egg-info/zip-safe
doubles/targets/__init__.py
doubles/targets/allowance_target.py
doubles/targets/expectation_target.py
doubles/targets/patch_target.py